ol_openedx_checkout_external/__init__.py
ol_openedx_checkout_external/app.py
ol_openedx_checkout_external/exceptions.py
ol_openedx_checkout_external/urls.py
ol_openedx_checkout_external/views.py
ol_openedx_checkout_external/settings/__init__.py
ol_openedx_checkout_external/settings/common.py
ol_openedx_checkout_external/settings/production.py
ol_openedx_checkout_external-0.2.0.dist-info/METADATA
ol_openedx_checkout_external-0.2.0.dist-info/WHEEL
ol_openedx_checkout_external-0.2.0.dist-info/entry_points.txt
ol_openedx_checkout_external-0.2.0.dist-info/licenses/LICENSE.txt
ol_openedx_checkout_external-0.2.0.dist-info/RECORD
